no_utils.py
no_utils-1.0.0.dist-info/LICENSE
no_utils-1.0.0.dist-info/METADATA
no_utils-1.0.0.dist-info/WHEEL
no_utils-1.0.0.dist-info/top_level.txt
no_utils-1.0.0.dist-info/RECORD
