Metadata-Version: 2.1
Name: no_utils
Version: 1.0.0
Summary: Python Module to enable running tasks inside threads based on cron schedule
Home-page: https://github.com/FrdAlex/no_utils
Author: Alexandru Furdui
Author-email: alexandru.vlad.furdui@gmail.com
License: MIT
Classifier: Programming Language :: Python :: 3
Classifier: License :: OSI Approved :: GNU Affero General Public License v3 or later (AGPLv3+)
Classifier: Operating System :: OS Independent
License-File: LICENSE
